kirpi/__init__.py
kirpi/base.py
kirpi/cli.py
kirpi/config.py
kirpi/types.py
kirpi/utils.py
kirpi-1.0.0.dist-info/entry_points.txt
kirpi-1.0.0.dist-info/LICENSE
kirpi-1.0.0.dist-info/WHEEL
kirpi-1.0.0.dist-info/METADATA
kirpi-1.0.0.dist-info/RECORD
