Metadata-Version: 2.1
Name: kirpi
Version: 1.0.0
Summary: Lightweight and simple ORM for Python (with psycopg)
Author-email: Ali <alisher.abdimuminov.2005@gmail.com>
Classifier: License :: OSI Approved :: MIT License
Requires-Dist: psycopg
Requires-Dist: click
Project-URL: Home, https://github.com/alisherabdimuminov/kirpi/
